henosis_cli.py
henosis_cli_tools/__init__.py
henosis_cli_tools/input_engine.py
henosis_cli_tools/tool_impl.py
henosis_tools-0.5.0.dist-info/METADATA
henosis_tools-0.5.0.dist-info/WHEEL
henosis_tools-0.5.0.dist-info/entry_points.txt
henosis_tools-0.5.0.dist-info/top_level.txt
henosis_tools-0.5.0.dist-info/RECORD
