Metadata-Version: 2.4
Name: henosis-tools
Version: 0.5.0
Summary: henosis-tools — standalone local filesystem and command tools with sandboxing and a simplified multi-file patch format.
Author-email: henosis <henosis@henosis.us>
License-Expression: LicenseRef-Proprietary
Project-URL: Homepage, https://henosis.us
Project-URL: Contact, https://henosis.us/contact
Keywords: henosis,tools,filesystem,sandbox,patch,subprocess,cli
Classifier: Programming Language :: Python :: 3
Classifier: Programming Language :: Python :: 3 :: Only
Classifier: Operating System :: OS Independent
Classifier: Environment :: Console
Classifier: Topic :: Utilities
Classifier: Intended Audience :: Developers
Requires-Python: >=3.9
